Metadata-Version: 2.1
Name: tino
Version: 0.0.1
Summary: API Framework built on MsgPack and Redis Protocol
Home-page: https://github.com/hansonkd/tino
Author: Kyle Hanson
Author-email: me@khanson.io
License: MIT
Platform: UNKNOWN
Classifier: Development Status :: 3 - Alpha
Classifier: Intended Audience :: Developers
Classifier: Operating System :: OS Independent
Classifier: Programming Language :: Python :: 3.6
Classifier: Programming Language :: Python :: 3.7
Classifier: Programming Language :: Python :: 3.8
Requires-Python: >=3.6
